[
  {
    "tag": "Start",
    "tagClass": "tag-default tag-accent",
    "title": "MVP sau aplicație simplă",
    "descr": "O aplicație internă sau un MVP funcțional construit rapid, cu funcțiile esențiale necesare pentru a valida și porni.",
    "currency": "€",
    "amount": "3.000+",
    "period": "/proiect",
    "timeline": "Durată orientativă: 4-8 săptămâni",
    "btnText": "Cere o estimare",
    "btnHref": "/contact",
    "features": [
      "analiză cerințe și arhitectură funcțională",
      "frontend și backend integrate",
      "autentificare și roluri de bază",
      "deploy pe infrastructura ta",
      "suport 30 zile după lansare"
    ],
    "linkText": "Ai nevoie de altceva? Hai să discutăm.",
    "linkHref": "/contact"
  },
  {
    "tag": "Cel mai cerut",
    "tagClass": "tag-default tag-additional",
    "title": "Platformă completă",
    "descr": "Aplicație complexă cu multiple module, integrări, dashboard-uri, raportare și fluxuri custom pentru operațiunile tale.",
    "currency": "€",
    "amount": "7.000+",
    "period": "/proiect",
    "timeline": "Durată orientativă: 3-6 luni",
    "btnText": "Discută proiectul",
    "btnHref": "/contact",
    "features": [
      "audit procese + arhitectură tehnică completă",
      "module multiple cu fluxuri custom",
      "integrări API cu sistemele existente",
      "dashboard-uri, rapoarte și vizibilitate",
      "suport prioritar + demo-uri regulate"
    ],
    "linkText": "Vrei o ofertă pe nevoia ta exactă? Scrie-ne.",
    "linkHref": "/contact",
    "best": true
  },
  {
    "tag": "Abonament lunar",
    "tagClass": "tag-default",
    "title": "Mentenanță + Evoluție",
    "descr": "Ne ocupăm de stabilitate, securitate și dezvoltare continuă — aplicația ta crește fără să devină blocaj tehnic.",
    "currency": "€",
    "amount": "300+",
    "period": "/lună",
    "timeline": "Include mentenanță, suport și ore de dezvoltare",
    "btnText": "Solicită abonament",
    "btnHref": "/contact",
    "features": [
      "monitorizare, backup și actualizări de securitate",
      "rezolvare bug-uri și intervenții urgente",
      "ore de dezvoltare incluse (până la 4/lună)",
      "suport tehnic prioritar (răspuns în 24h)",
      "raport lunar + plan de evoluție"
    ],
    "linkText": "Nu te încadrezi într-un pachet? Construim unul custom.",
    "linkHref": "/contact"
  }
]
