[
  {
    "authorPhoto": "/img/avatars/300x300_ava-03.webp",
    "authorPhotoWidth": 300,
    "authorPhotoHeight": 300,
    "authorName": "Andrei Popescu",
    "authorPosition": "Manager de produs la",
    "authorCompany": "Instant Design",
    "authorCompanyUrl": "#",
    "rating": 5,
    "text": "Colaborarea a fost clară și foarte bine structurată. Echipa a înțeles rapid ce trebuia construit și a transformat cerințele noastre într-un produs digital ușor de folosit și ușor de extins.",
    "projectPage": "#",
    "testimonialImage": "/img/testimonials/1400x1200_t01.webp",
    "testimonialImageWidth": 1433,
    "testimonialImageHeight": 1200
  },
  {
    "authorPhoto": "/img/avatars/300x300_ava-04.webp",
    "authorPhotoWidth": 300,
    "authorPhotoHeight": 300,
    "authorName": "Mara Ionescu",
    "authorPosition": "Coordonator marketing la",
    "authorCompany": "Eye Candy",
    "authorCompanyUrl": "#",
    "rating": 5,
    "text": "Am apreciat combinația dintre atenția la detalii, execuția tehnică și viteza de reacție. După lansare, feedback-ul primit de la clienți a fost imediat mai bun.",
    "projectPage": "#",
    "testimonialImage": "/img/testimonials/1400x1200_t02.webp",
    "testimonialImageWidth": 1433,
    "testimonialImageHeight": 1200
  }
]
